commbotpy/__init__.py
commbotpy-0.0.0.dist-info/METADATA
commbotpy-0.0.0.dist-info/WHEEL
commbotpy-0.0.0.dist-info/top_level.txt
commbotpy-0.0.0.dist-info/RECORD
