Metadata-Version: 2.4
Name: commbotpy
Version: 0.0.0
Summary: Lightweight serial comms lib between Python and Arduino using pub/sub like ROS.
Author: Fikri Rivandi
Author-email: fixri2104@gmail.com
Keywords: arduino,serial,robotics,communication,pubsub
Classifier: Programming Language :: Python :: 3
Classifier: Operating System :: OS Independent
Requires-Dist: pyserial
Dynamic: author
Dynamic: author-email
Dynamic: classifier
Dynamic: keywords
Dynamic: requires-dist
Dynamic: summary
